tao_byom/__init__.py
tao_byom/converter.py
tao_byom/version.py
tao_byom/entrypoint/__init__.py
tao_byom/entrypoint/entrypoint.py
tao_byom/layers/__init__.py
tao_byom/layers/activation_layers.py
tao_byom/layers/constant_layers.py
tao_byom/layers/convolution_layers.py
tao_byom/layers/custom_layers.py
tao_byom/layers/elementwise_layers.py
tao_byom/layers/layers.py
tao_byom/layers/linear_layers.py
tao_byom/layers/normalization_layers.py
tao_byom/layers/operation_layers.py
tao_byom/layers/padding_layers.py
tao_byom/layers/pooling_layers.py
tao_byom/layers/reshape_layers.py
tao_byom/layers/tensor_layer.py
tao_byom/layers/upsampling_layers.py
tao_byom/license/EULA.pdf
tao_byom/license/__init__.py
tao_byom/third_party/__init__.py
tao_byom/third_party/nn_ops.py
tao_byom/third_party/tensorflow_backend.py
tao_byom/utils/__init__.py
tao_byom/utils/convert_utils.py
tao_byom/utils/model_utils.py
nvidia_tao_byom-0.0.11.2.dist-info/METADATA
nvidia_tao_byom-0.0.11.2.dist-info/WHEEL
nvidia_tao_byom-0.0.11.2.dist-info/entry_points.txt
nvidia_tao_byom-0.0.11.2.dist-info/top_level.txt
nvidia_tao_byom-0.0.11.2.dist-info/RECORD
